akita_har/__init__.py
akita_har/models.py
akita_har-0.0.2.dist-info/LICENSE
akita_har-0.0.2.dist-info/METADATA
akita_har-0.0.2.dist-info/WHEEL
akita_har-0.0.2.dist-info/top_level.txt
akita_har-0.0.2.dist-info/RECORD
