Metadata-Version: 2.1
Name: akita-har
Version: 0.0.2
Summary: Utilities for working with HTTP Archive (HAR) files
Home-page: https://github.com/akitasoftware/akita-python-har
Author: Cole Schlesinger
Author-email: cole@akitasoftware.com
License: UNKNOWN
Platform: UNKNOWN
Classifier: Programming Language :: Python :: 3
Classifier: License :: OSI Approved :: BSD License
Classifier: Operating System :: OS Independent
Requires-Python: >=3.6
Requires-Dist: pydantic
